{
    "$comment": "Version: v3.4.0 generated at 2020-01-23T11:00:02+01:00",
    "$schema": "http://json-schema.org/schema#",
    "$id": "https://schema.fintlabs.no/utdanning/elevforhold.json",
    "type": "object",
    "properties": {
        "beskrivelse": {
            "type": "string"
        },
        "systemId": {
            "type": "object", "$ref": "https://schema.fintlabs.no/felles/identifikator.json"
        },
        "_links": {
            "type": "object",
            "properties": {
                "basisgruppe": {
                    "type": "array",
                    "items": {
                        "type": "object",
                        "properties": {
                            "href": {
                                "type": "string",
                                "format": "uri"
                            }
                        },
                        "required": [ "href" ]
                    }
                }, 
                "elev": {
                    "type": "array",
                    "minItems": 1,
                    "maxItems": 1,
                    "items": {
                        "type": "object",
                        "properties": {
                            "href": {
                                "type": "string",
                                "format": "uri"
                            }
                        },
                        "required": [ "href" ]
                    }
                }, 
                "kategori": {
                    "type": "array",
                    "maxItems": 1,
                    "items": {
                        "type": "object",
                        "properties": {
                            "href": {
                                "type": "string",
                                "format": "uri"
                            }
                        },
                        "required": [ "href" ]
                    }
                }, 
                "skole": {
                    "type": "array",
                    "minItems": 1,
                    "maxItems": 1,
                    "items": {
                        "type": "object",
                        "properties": {
                            "href": {
                                "type": "string",
                                "format": "uri"
                            }
                        },
                        "required": [ "href" ]
                    }
                }, 
                "eksamensgruppe": {
                    "type": "array",
                    "items": {
                        "type": "object",
                        "properties": {
                            "href": {
                                "type": "string",
                                "format": "uri"
                            }
                        },
                        "required": [ "href" ]
                    }
                }, 
                "kontaktlarergruppe": {
                    "type": "array",
                    "items": {
                        "type": "object",
                        "properties": {
                            "href": {
                                "type": "string",
                                "format": "uri"
                            }
                        },
                        "required": [ "href" ]
                    }
                }, 
                "programomrade": {
                    "type": "array",
                    "maxItems": 1,
                    "items": {
                        "type": "object",
                        "properties": {
                            "href": {
                                "type": "string",
                                "format": "uri"
                            }
                        },
                        "required": [ "href" ]
                    }
                }, 
                "undervisningsgruppe": {
                    "type": "array",
                    "items": {
                        "type": "object",
                        "properties": {
                            "href": {
                                "type": "string",
                                "format": "uri"
                            }
                        },
                        "required": [ "href" ]
                    }
                }, 
                "vurdering": {
                    "type": "array",
                    "items": {
                        "type": "object",
                        "properties": {
                            "href": {
                                "type": "string",
                                "format": "uri"
                            }
                        },
                        "required": [ "href" ]
                    }
                }, 
                "fravar": {
                    "type": "array",
                    "items": {
                        "type": "object",
                        "properties": {
                            "href": {
                                "type": "string",
                                "format": "uri"
                            }
                        },
                        "required": [ "href" ]
                    }
                }, 
                "medlemskap": {
                    "type": "array",
                    "items": {
                        "type": "object",
                        "properties": {
                            "href": {
                                "type": "string",
                                "format": "uri"
                            }
                        },
                        "required": [ "href" ]
                    }
                }, 
                "self": {
                    "type": "array",
                    "minItems": 1,
                    "maxItems": 1,
                    "items": {
                        "type": "object",
                        "properties": {
                            "href": {
                                "type": "string",
                                "format": "uri"
                            }
                        },
                        "required": [ "href" ]
                    }
                }
            },
            "additionalProperties": {
                "type": "array",
                "items": {
                    "type": "object",
                    "properties": {
                        "href": {
                            "type": "string",
                            "format": "uri"
                        }
                    },
                    "required": [ "href" ]
                }
            },
            "required": [
                "elev", 
                "skole", 
                "self"
            ]
        }
    },
    "required": [
        "beskrivelse", 
        "systemId", 
        "_links"
    ]
}
